{"success":true,"logs":[{"ts":"00:03:30","tag":"JOIN","msg":"User e1h2mu9v4fa94i7 joining room room_1772006580410"},{"ts":"00:03:30","tag":"JOIN","msg":"User e1h2mu9v4fa94i7 joining room room_1772006580410"},{"ts":"00:03:30","tag":"JOIN","msg":"User e1h2mu9v4fa94i7 joining room room_1772006580410"},{"ts":"00:03:30","tag":"JOIN","msg":"User e1h2mu9v4fa94i7 joining room room_1772006580410"},{"ts":"00:03:30","tag":"JOIN","msg":"User e1h2mu9v4fa94i7 joining room room_1772006580410"},{"ts":"00:03:30","tag":"JOIN","msg":"User e1h2mu9v4fa94i7 joining room room_1772006580410"},{"ts":"00:03:30","tag":"JOIN","msg":"User e1h2mu9v4fa94i7 joining room room_1772006580410"},{"ts":"00:03:30","tag":"JOIN","msg":"User e1h2mu9v4fa94i7 joining room room_1772006580410"},{"ts":"00:03:30","tag":"JOIN","msg":"User e1h2mu9v4fa94i7 joining room room_1772006580410"},{"ts":"00:03:30","tag":"JOIN","msg":"User e1h2mu9v4fa94i7 joining room room_1772006580410"},{"ts":"00:03:30","tag":"JOIN","msg":"User e1h2mu9v4fa94i7 joining room room_1772006580410"},{"ts":"00:03:30","tag":"JOIN","msg":"User e1h2mu9v4fa94i7 joining room room_1772006580410"},{"ts":"00:03:30","tag":"JOIN","msg":"User e1h2mu9v4fa94i7 joining room room_1772006580410"},{"ts":"00:03:30","tag":"JOIN","msg":"User e1h2mu9v4fa94i7 joining room room_1772006580410"},{"ts":"00:03:30","tag":"JOIN","msg":"User e1h2mu9v4fa94i7 joining room room_1772006580410"},{"ts":"00:03:30","tag":"JOIN","msg":"User e1h2mu9v4fa94i7 joining room room_1772006580410"},{"ts":"00:03:30","tag":"JOIN","msg":"User e1h2mu9v4fa94i7 joining room room_1772006580410"},{"ts":"00:03:30","tag":"JOIN","msg":"User e1h2mu9v4fa94i7 joining room room_1772006580410"},{"ts":"00:03:30","tag":"JOIN","msg":"User e1h2mu9v4fa94i7 joining room room_1772006580410"},{"ts":"00:03:30","tag":"JOIN","msg":"User e1h2mu9v4fa94i7 joining room room_1772006580410"},{"ts":"00:03:30","tag":"JOIN","msg":"User e1h2mu9v4fa94i7 joining room room_1772006580410"},{"ts":"00:03:30","tag":"JOIN","msg":"User e1h2mu9v4fa94i7 joining room room_1772006580410"},{"ts":"00:03:30","tag":"JOIN","msg":"User e1h2mu9v4fa94i7 joining room room_1772006580410"},{"ts":"00:03:30","tag":"JOIN","msg":"User e1h2mu9v4fa94i7 joining room room_1772006580410"},{"ts":"00:03:30","tag":"JOIN","msg":"User e1h2mu9v4fa94i7 joining room room_1772006580410"},{"ts":"00:03:30","tag":"JOIN","msg":"User e1h2mu9v4fa94i7 joining room room_1772006580410"},{"ts":"00:03:30","tag":"JOIN","msg":"User e1h2mu9v4fa94i7 joining room room_1772006580410"},{"ts":"00:03:30","tag":"JOIN","msg":"User e1h2mu9v4fa94i7 joining room room_1772006580410"},{"ts":"00:03:30","tag":"JOIN","msg":"User e1h2mu9v4fa94i7 joining room room_1772006580410"},{"ts":"00:03:30","tag":"JOIN","msg":"User e1h2mu9v4fa94i7 joining room room_1772006580410"},{"ts":"00:03:30","tag":"JOIN","msg":"User e1h2mu9v4fa94i7 joining room room_1772006580410"},{"ts":"00:03:30","tag":"JOIN","msg":"User e1h2mu9v4fa94i7 joining room room_1772006580410"},{"ts":"00:03:30","tag":"JOIN","msg":"User e1h2mu9v4fa94i7 joining room room_1772006580410"},{"ts":"00:03:30","tag":"JOIN","msg":"User e1h2mu9v4fa94i7 joining room room_1772006580410"},{"ts":"00:03:30","tag":"JOIN","msg":"User e1h2mu9v4fa94i7 joining room room_1772006580410"},{"ts":"00:03:30","tag":"JOIN","msg":"User e1h2mu9v4fa94i7 joining room room_1772006580410"},{"ts":"00:03:30","tag":"JOIN","msg":"User e1h2mu9v4fa94i7 joining room room_1772006580410"},{"ts":"00:03:30","tag":"JOIN","msg":"User e1h2mu9v4fa94i7 joining room room_1772006580410"},{"ts":"00:03:30","tag":"JOIN","msg":"User e1h2mu9v4fa94i7 joining room room_1772006580410"},{"ts":"00:03:30","tag":"JOIN","msg":"User e1h2mu9v4fa94i7 joining room room_1772006580410"},{"ts":"00:03:30","tag":"JOIN","msg":"User e1h2mu9v4fa94i7 joining room room_1772006580410"},{"ts":"00:03:30","tag":"JOIN","msg":"User e1h2mu9v4fa94i7 joining room room_1772006580410"},{"ts":"00:03:30","tag":"JOIN","msg":"User e1h2mu9v4fa94i7 joining room room_1772006580410"},{"ts":"00:03:30","tag":"JOIN","msg":"User e1h2mu9v4fa94i7 joining room room_1772006580410"},{"ts":"00:03:30","tag":"JOIN","msg":"User e1h2mu9v4fa94i7 joining room room_1772006580410"},{"ts":"00:03:30","tag":"JOIN","msg":"User e1h2mu9v4fa94i7 joining room room_1772006580410"},{"ts":"00:03:30","tag":"JOIN","msg":"User e1h2mu9v4fa94i7 joining room room_1772006580410"},{"ts":"00:03:30","tag":"JOIN","msg":"User e1h2mu9v4fa94i7 joining room room_1772006580410"},{"ts":"00:03:30","tag":"JOIN","msg":"User e1h2mu9v4fa94i7 joining room room_1772006580410"},{"ts":"00:03:30","tag":"JOIN","msg":"User e1h2mu9v4fa94i7 joining room room_1772006580410"},{"ts":"00:03:30","tag":"JOIN","msg":"User e1h2mu9v4fa94i7 joining room room_1772006580410"},{"ts":"00:03:30","tag":"JOIN","msg":"User e1h2mu9v4fa94i7 joining room room_1772006580410"},{"ts":"00:03:30","tag":"JOIN","msg":"User e1h2mu9v4fa94i7 joining room room_1772006580410"},{"ts":"00:03:30","tag":"JOIN","msg":"User e1h2mu9v4fa94i7 joining room room_1772006580410"},{"ts":"00:03:30","tag":"JOIN","msg":"User e1h2mu9v4fa94i7 joining room room_1772006580410"},{"ts":"00:03:30","tag":"JOIN","msg":"User e1h2mu9v4fa94i7 joining room room_1772006580410"},{"ts":"00:03:30","tag":"JOIN","msg":"User e1h2mu9v4fa94i7 joining room room_1772006580410"},{"ts":"00:03:30","tag":"JOIN","msg":"User e1h2mu9v4fa94i7 joining room room_1772006580410"},{"ts":"00:03:30","tag":"JOIN","msg":"User e1h2mu9v4fa94i7 joining room room_1772006580410"},{"ts":"00:03:30","tag":"JOIN","msg":"User e1h2mu9v4fa94i7 joining room room_1772006580410"},{"ts":"00:03:30","tag":"JOIN","msg":"User e1h2mu9v4fa94i7 joining room room_1772006580410"},{"ts":"00:03:30","tag":"JOIN","msg":"User e1h2mu9v4fa94i7 joining room room_1772006580410"},{"ts":"00:03:30","tag":"JOIN","msg":"User e1h2mu9v4fa94i7 joining room room_1772006580410"},{"ts":"00:03:30","tag":"JOIN","msg":"User e1h2mu9v4fa94i7 joining room room_1772006580410"},{"ts":"00:03:30","tag":"JOIN","msg":"User e1h2mu9v4fa94i7 joining room room_1772006580410"},{"ts":"00:03:30","tag":"JOIN","msg":"User e1h2mu9v4fa94i7 joining room room_1772006580410"},{"ts":"00:03:30","tag":"JOIN","msg":"User e1h2mu9v4fa94i7 joining room room_1772006580410"},{"ts":"00:03:30","tag":"JOIN","msg":"User e1h2mu9v4fa94i7 joining room room_1772006580410"},{"ts":"00:03:30","tag":"JOIN","msg":"User e1h2mu9v4fa94i7 joining room room_1772006580410"},{"ts":"00:03:30","tag":"JOIN","msg":"User e1h2mu9v4fa94i7 joining room room_1772006580410"},{"ts":"00:03:30","tag":"JOIN","msg":"User e1h2mu9v4fa94i7 joining room room_1772006580410"},{"ts":"00:03:30","tag":"JOIN","msg":"User e1h2mu9v4fa94i7 joining room room_1772006580410"},{"ts":"00:03:30","tag":"JOIN","msg":"User e1h2mu9v4fa94i7 joining room room_1772006580410"},{"ts":"00:03:30","tag":"JOIN","msg":"User e1h2mu9v4fa94i7 joining room room_1772006580410"},{"ts":"00:03:30","tag":"JOIN","msg":"User e1h2mu9v4fa94i7 joining room room_1772006580410"},{"ts":"00:03:30","tag":"JOIN","msg":"User e1h2mu9v4fa94i7 joining room room_1772006580410"},{"ts":"00:03:30","tag":"JOIN","msg":"User e1h2mu9v4fa94i7 joining room room_1772006580410"},{"ts":"00:03:30","tag":"JOIN","msg":"User e1h2mu9v4fa94i7 joining room room_1772006580410"},{"ts":"00:03:30","tag":"JOIN","msg":"User e1h2mu9v4fa94i7 joining room room_1772006580410"},{"ts":"00:03:30","tag":"JOIN","msg":"User e1h2mu9v4fa94i7 joining room room_1772006580410"},{"ts":"00:03:30","tag":"JOIN","msg":"User e1h2mu9v4fa94i7 joining room room_1772006580410"},{"ts":"00:03:30","tag":"JOIN","msg":"User e1h2mu9v4fa94i7 joining room room_1772006580410"},{"ts":"00:03:30","tag":"JOIN","msg":"User e1h2mu9v4fa94i7 joining room room_1772006580410"},{"ts":"00:03:30","tag":"JOIN","msg":"User e1h2mu9v4fa94i7 joining room room_1772006580410"},{"ts":"00:03:30","tag":"JOIN","msg":"User e1h2mu9v4fa94i7 joining room room_1772006580410"},{"ts":"00:03:30","tag":"JOIN","msg":"User e1h2mu9v4fa94i7 joining room room_1772006580410"},{"ts":"00:03:30","tag":"JOIN","msg":"User e1h2mu9v4fa94i7 joining room room_1772006580410"},{"ts":"00:03:30","tag":"JOIN","msg":"User e1h2mu9v4fa94i7 joining room room_1772006580410"},{"ts":"00:03:30","tag":"JOIN","msg":"User e1h2mu9v4fa94i7 joining room room_1772006580410"},{"ts":"00:03:30","tag":"JOIN","msg":"User e1h2mu9v4fa94i7 joining room room_1772006580410"},{"ts":"00:03:31","tag":"JOIN","msg":"User e1h2mu9v4fa94i7 joining room room_1772006580410"},{"ts":"00:03:31","tag":"JOIN","msg":"User e1h2mu9v4fa94i7 joining room room_1772006580410"},{"ts":"00:03:31","tag":"JOIN","msg":"User e1h2mu9v4fa94i7 joining room room_1772006580410"},{"ts":"00:03:31","tag":"JOIN","msg":"User e1h2mu9v4fa94i7 joining room room_1772006580410"},{"ts":"00:03:31","tag":"JOIN","msg":"User e1h2mu9v4fa94i7 joining room room_1772006580410"},{"ts":"00:03:31","tag":"JOIN","msg":"User e1h2mu9v4fa94i7 joining room room_1772006580410"},{"ts":"00:03:31","tag":"JOIN","msg":"User e1h2mu9v4fa94i7 joining room room_1772006580410"},{"ts":"00:03:31","tag":"JOIN","msg":"User e1h2mu9v4fa94i7 joining room room_1772006580410"},{"ts":"00:03:31","tag":"JOIN","msg":"User e1h2mu9v4fa94i7 joining room room_1772006580410"},{"ts":"00:03:31","tag":"JOIN","msg":"User e1h2mu9v4fa94i7 joining room room_1772006580410"}]}
